MANIFEST.in
README.rst
bootstrap-buildout.py
buildout.cfg
setup.py
version.txt
antispoofing/__init__.py
antispoofing.fusion.egg-info/PKG-INFO
antispoofing.fusion.egg-info/SOURCES.txt
antispoofing.fusion.egg-info/dependency_links.txt
antispoofing.fusion.egg-info/entry_points.txt
antispoofing.fusion.egg-info/namespace_packages.txt
antispoofing.fusion.egg-info/requires.txt
antispoofing.fusion.egg-info/top_level.txt
antispoofing/fusion/__init__.py
antispoofing/fusion/fusion/__init__.py
antispoofing/fusion/fusion/fusion.py
antispoofing/fusion/ml/__init__.py
antispoofing/fusion/ml/perf_fusion.py
antispoofing/fusion/normalizer/2dnorm.py
antispoofing/fusion/normalizer/__init__.py
antispoofing/fusion/normalizer/minmax_norm.py
antispoofing/fusion/normalizer/normalizer.py
antispoofing/fusion/normalizer/znorm.py
antispoofing/fusion/readers/__init__.py
antispoofing/fusion/readers/score_fusion_reader.py
antispoofing/fusion/score_fusion/LDAFusion.py
antispoofing/fusion/score_fusion/LLRFusion.py
antispoofing/fusion/score_fusion/SUMFusion.py
antispoofing/fusion/score_fusion/SVMFusion.py
antispoofing/fusion/score_fusion/__init__.py
antispoofing/fusion/score_fusion/score_fusion.py
antispoofing/fusion/script/__init__.py
antispoofing/fusion/script/find_valid_frames.py
antispoofing/fusion/script/frame_by_frame_analysis.py
antispoofing/fusion/script/fuse_scores.py
antispoofing/fusion/script/fusion_scores.py
antispoofing/fusion/script/stub.py
antispoofing/fusion/script/time_analysis.py
antispoofing/fusion/script/venn.py