Metadata-Version: 1.0
Name: antispoofing.fusion
Version: 2.0.0
Summary: Complementary countermeasures for detecting scenic face spoofing attacks
Home-page: http://pypi.python.org/pypi/antispoofing.fusion
Author: Jukka Komulainen
Author-email: jukmaatt@ee.oulu.fi
License: GPLv3
Platform: UNKNOWN
